sweden_crs_transformations/__init__.py
sweden_crs_transformations/crs_coordinate.py
sweden_crs_transformations/crs_projection.py
sweden_crs_transformations/mighty_little_geodesy/__init__.py
sweden_crs_transformations/mighty_little_geodesy/_gauss_kreuger.py
sweden_crs_transformations/mighty_little_geodesy/_gauss_kreuger_parameter_object.py
sweden_crs_transformations/mighty_little_geodesy/_lat_lon.py
sweden_crs_transformations/transformation/__init__.py
sweden_crs_transformations/transformation/_transform_strategy.py
sweden_crs_transformations/transformation/_transform_strategy_from_sweref99_or_rt90_to_wgs84.py
sweden_crs_transformations/transformation/_transform_strategy_from_sweref99_or_rt90_to_wgs84_and_then_to_real_target.py
sweden_crs_transformations/transformation/_transform_strategy_from_wgs84_to_sweref99_or_rt90.py
sweden_crs_transformations/transformation/_transformer.py
sweden_crs_transformations-1.0.0.dist-info/AUTHORS.rst
sweden_crs_transformations-1.0.0.dist-info/LICENSE
sweden_crs_transformations-1.0.0.dist-info/METADATA
sweden_crs_transformations-1.0.0.dist-info/WHEEL
sweden_crs_transformations-1.0.0.dist-info/top_level.txt
sweden_crs_transformations-1.0.0.dist-info/RECORD
