Metadata-Version: 2.1
Name: sweden-crs-transformations
Version: 1.0.0
Summary: Python library for transformation of geographic coordinates between WGS84 and the Swedish coordinate reference systems SWEREF99 and RT90
Home-page: https://github.com/TomasJohansson/sweden_crs_transformations_4python
Author: Tomas Johansson
Author-email: pypi@programmerare.com
License: MIT license
Keywords: WGS84,RT90,SWEREF99,SWEREF99TM,CRS,Coordinate Reference Systems
Platform: UNKNOWN
Classifier: Development Status :: 5 - Production/Stable
Classifier: Intended Audience :: Developers
Classifier: License :: OSI Approved :: MIT License
Classifier: Natural Language :: English
Classifier: Topic :: Scientific/Engineering :: GIS
Classifier: Programming Language :: Python :: 3
Classifier: Programming Language :: Python :: 3.8
Classifier: Programming Language :: Python :: 3.9
Classifier: Typing :: Typed
Requires-Python: >=3.8
